LICENCE.txt
MANIFEST.in
README.md
necpp.py
necpp_wrap.c
setup.cfg
setup.py
../necpp_src/example/test.py
example/antenna_util.py
example/different_material.py
example/impedance_plot.py
example/monopole.py
example/optimized.py
necpp.egg-info/PKG-INFO
necpp.egg-info/SOURCES.txt
necpp.egg-info/dependency_links.txt
necpp.egg-info/top_level.txt
necpp_src/config.h
necpp_src/example/test.py
necpp_src/src/AntennaInput.h
necpp_src/src/BaseInput.h
necpp_src/src/CurrentInput.h
necpp_src/src/PowerBudget.h
necpp_src/src/RadiationInput.h
necpp_src/src/XGetopt.cpp
necpp_src/src/XGetopt.h
necpp_src/src/atlas_check.cpp
necpp_src/src/c_evlcom.cpp
necpp_src/src/c_evlcom.h
necpp_src/src/c_geometry.cpp
necpp_src/src/c_geometry.h
necpp_src/src/c_ggrid.cpp
necpp_src/src/c_ggrid.h
necpp_src/src/c_plot_card.cpp
necpp_src/src/c_plot_card.h
necpp_src/src/common.h
necpp_src/src/electromag.cpp
necpp_src/src/electromag.h
necpp_src/src/libNEC.cpp
necpp_src/src/libnecpp.h
necpp_src/src/math_util.h
necpp_src/src/matrix_algebra.cpp
necpp_src/src/matrix_algebra.h
necpp_src/src/misc.cpp
necpp_src/src/misc.h
necpp_src/src/nec2cpp.h
necpp_src/src/nec_context.cpp
necpp_src/src/nec_context.h
necpp_src/src/nec_debug.h
necpp_src/src/nec_exception.cpp
necpp_src/src/nec_exception.h
necpp_src/src/nec_ground.cpp
necpp_src/src/nec_ground.h
necpp_src/src/nec_output.cpp
necpp_src/src/nec_output.h
necpp_src/src/nec_radiation_pattern.cpp
necpp_src/src/nec_radiation_pattern.h
necpp_src/src/nec_results.cpp
necpp_src/src/nec_results.h
necpp_src/src/nec_structure_currents.cpp
necpp_src/src/nec_structure_currents.h
necpp_src/src/nec_wire.h
necpp_src/src/safe_array.h
necpp_src/src/typesafe_stdint.h