Metadata-Version: 2.1
Name: necpp
Version: 1.7.3.5
Summary: Python Antenna Simulation Module (nec2++) C-style interface
Home-page: http://github.com/tmolteno/necpp
Author: Tim Molteno
Author-email: tim@physics.otago.ac.nz
License: GPLv2
Keywords: nec2 nec2++ antenna electromagnetism radio
Platform: UNKNOWN
Classifier: Development Status :: 5 - Production/Stable
Classifier: Topic :: Scientific/Engineering
Classifier: Topic :: Communications :: Ham Radio
Classifier: License :: OSI Approved :: GNU General Public License v2 (GPLv2)
Classifier: Programming Language :: Python :: 2
Classifier: Programming Language :: Python :: 2.7
Classifier: Programming Language :: Python :: 3
Classifier: Programming Language :: Python :: 3.3
Classifier: Programming Language :: Python :: 3.4
Classifier: Programming Language :: Python :: 3.5
Classifier: Intended Audience :: Science/Research
